CHANGELOG.txt
LICENSE.txt
MANIFEST.in
README.txt
setup.py
base_calc/__init__.py
base_calc.egg-info/PKG-INFO
base_calc.egg-info/SOURCES.txt
base_calc.egg-info/dependency_links.txt
base_calc.egg-info/top_level.txt